encoders/__init__.py
utils/__init__.py
utils/debuggers.py
utils/slack.py
htk_lite-1.0.1.dist-info/LICENSE.md
htk_lite-1.0.1.dist-info/METADATA
htk_lite-1.0.1.dist-info/WHEEL
htk_lite-1.0.1.dist-info/entry_points.txt
htk_lite-1.0.1.dist-info/top_level.txt
htk_lite-1.0.1.dist-info/RECORD
