Metadata-Version: 2.1
Name: htk-lite
Version: 1.0.1
Summary: Python utilities by Hacktoolkit.
Home-page: https://github.com/hacktoolkit/python-htk-lite
Author: Hacktoolkit
Author-email: hello@hacktoolkit.com
License: MIT
Keywords: python debugging slack requests apis
Platform: UNKNOWN
Classifier: Development Status :: 3 - Alpha
Classifier: Intended Audience :: Developers
Classifier: Topic :: Text Processing :: General
Classifier: License :: OSI Approved :: MIT License
Classifier: Programming Language :: Python :: 2
Classifier: Programming Language :: Python :: 2.7
Classifier: Programming Language :: Python :: 3
License-File: LICENSE.md
Provides-Extra: dev
Provides-Extra: test
